LICENSE
MANIFEST.in
README.rst
setup.cfg
setup.py
labelsync/__init__.py
labelsync/clients.py
labelsync/io.py
labelsync/logic.py
labelsync/util.py
labelsync/web.py
labelsync.egg-info/PKG-INFO
labelsync.egg-info/SOURCES.txt
labelsync.egg-info/dependency_links.txt
labelsync.egg-info/not-zip-safe
labelsync.egg-info/requires.txt
labelsync.egg-info/top_level.txt
labelsync/templates/create_master.html
labelsync/templates/index.html
labelsync/templates/label_form.html
labelsync/templates/login_form.html
labelsync/templates/repo_form.html
test/integration_test.py
test/io_test.py
test/nonexistent_cache
test/resolving_test.py
test/test_cache