Metadata-Version: 1.1
Name: labelsync
Version: 0.1.1
Summary: Web app for synchronization of issue labels across repositories
Home-page: https://github.com/novotkry/mi-pyt-final
Author: Krystof Novotny
Author-email: novotkry@fit.cvut.cz
License: WTFPL
Keywords: label synchronization github gitlab
Platform: UNKNOWN
Classifier: Environment :: Web Environment
Classifier: Framework :: Flask
Classifier: Intended Audience :: Developers
Classifier: Intended Audience :: Education
Classifier: Intended Audience :: Information Technology
Classifier: Intended Audience :: Science/Research
Classifier: Natural Language :: English
Classifier: Programming Language :: Python
Classifier: Programming Language :: Python :: 3
Classifier: Programming Language :: Python :: 3.6
Classifier: Programming Language :: Python :: 3.7
Classifier: Topic :: Software Development
Classifier: Topic :: Utilities
